sjtu_lib_booking/__init__.py
sjtu_lib_booking/__main__.py
sjtu_lib_booking/booking.py
sjtu_lib_booking/models.py
sjtu_lib_booking-0.1.2.dist-info/LICENSE.md
sjtu_lib_booking-0.1.2.dist-info/METADATA
sjtu_lib_booking-0.1.2.dist-info/WHEEL
sjtu_lib_booking-0.1.2.dist-info/entry_points.txt
sjtu_lib_booking-0.1.2.dist-info/top_level.txt
sjtu_lib_booking-0.1.2.dist-info/RECORD
