Metadata-Version: 2.1
Name: sjtu-lib-booking
Version: 0.1.2
Summary: A simple script that helps you book a seat in library.
Home-page: https://github.com/PhotonQuantum/sjtu-lib-booking
Author: LightQuantum
Author-email: self@lightquantum.me
License: UNKNOWN
Platform: UNKNOWN
Classifier: Operating System :: OS Independent
Classifier: Programming Language :: Python :: 3.7
Classifier: Programming Language :: Python :: 3.8
Classifier: Programming Language :: Python :: 3 :: Only
Classifier: License :: OSI Approved :: GNU General Public License v3 (GPLv3)
Classifier: Environment :: Web Environment
Classifier: Intended Audience :: End Users/Desktop
Classifier: Topic :: Internet :: WWW/HTTP :: Dynamic Content
Requires-Dist: pysjtu[ocr] (>=0.3.2)
